{
    "cars": [
        {
            "type": "sedan",
            "brand": "Toyota",
            "model": "Corolla Hatch",
            "image": "toyota-corolla.png",
            "mileage": 10000,
            "fuel_type": "petrol",
            "seats": 5,
            "quantity": 3,
            "price_day": 90,
            "transmission": "automatic"
        },
        {
            "type": "sedan",
            "brand": "Kia",
            "model": "Rio",
            "image": "kia-rio.png",
            "mileage": 13000,
            "fuel_type": "petrol",
            "seats": 5,
            "quantity": 3,
            "price_day": 70,
            "transmission": "automatic"
        },
        {
            "type": "sedan",
            "brand": "Toyota",
            "model": "Yaris",
            "image": "toyota-yaris.png",
            "mileage": 18000,
            "fuel_type": "petrol",
            "seats": 5,
            "quantity": 2,
            "price_day": 40,
            "transmission": "automatic"
        },
        {
            "type": "SUV",
            "brand": "MG",
            "model": "HS",
            "image": "mg-hs.png",
            "mileage": 23000,
            "fuel_type": "petrol",
            "seats": 5,
            "quantity": 1,
            "price_day": 60,
            "transmission": "automatic"
        },
        {
            "type": "SUV",
            "brand": "VW",
            "model": "Tiguan",
            "image": "vw-tiguan.png",
            "mileage": 10720,
            "fuel_type": "petrol",
            "seats": 5,
            "quantity": 3,
            "price_day": 80,
            "transmission": "automatic"
        },
        {
            "type": "SUV",
            "brand": "Nissan",
            "model": "Juke",
            "image": "nissan-juke.png",
            "mileage": 10050,
            "fuel_type": "petrol",
            "seats": 5,
            "quantity": 1,
            "price_day": 100,
            "transmission": "automatic"
        },
        {
            "type": "SUV",
            "brand": "Toyota",
            "model": "RAV4",
            "image": "toyota-rav4.png",
            "mileage": 13400,
            "fuel_type": "petrol",
            "seats": 5,
            "quantity": 3,
            "price_day": 90,
            "transmission": "automatic"
        },
        {
            "type": "minivan",
            "brand": "Kia",
            "model": "Carnival",
            "image": "kia-carnival.jpg",
            "mileage": 20000,
            "fuel_type": "petrol",
            "seats": 8,
            "quantity": 3,
            "price_day": 300,
            "transmission": "automatic"
        },
        {
            "type": "SUV",
            "brand": "BYD",
            "model": "ATTO 3",
            "image": "byd-atto.png",
            "mileage": 9000,
            "fuel_type": "electric",
            "seats": 5,
            "quantity": 2,
            "price_day": 70,
            "transmission": "automatic"
        },
        {
            "type": "sedan",
            "brand": "BMW",
            "model": "2 Gran Coupe",
            "image": "bmw-2-gran-coupe.png",
            "mileage": 5000,
            "fuel_type": "petrol",
            "seats": 5,
            "quantity": 2,
            "price_day": 100,
            "transmission": "automatic"
        },
        {
            "type": "sedan",
            "brand": "BMW",
            "model": "3 Series",
            "image": "bmw-3series.png",
            "mileage": 8000,
            "fuel_type": "petrol",
            "seats": 5,
            "quantity": 1,
            "price_day": 100,
            "transmission": "automatic"
        },
        {
            "type": "sedan",
            "brand": "Tesla",
            "model": "Model 3",
            "image": "tesla-model3.png",
            "mileage": 3000,
            "fuel_type": "electric",
            "seats": 5,
            "quantity": 1,
            "price_day": 100,
            "transmission": "automatic"
        },
        {
            "type": "wagon",
            "brand": "Subaru",
            "model": "Outback",
            "image": "subaru-outback.png",
            "mileage": 5000,
            "fuel_type": "petrol",
            "seats": 5,
            "quantity": 2,
            "price_day": 80,
            "transmission": "automatic"
        },
        {
            "type": "wagon",
            "brand": "Audi",
            "model": "A4 Avant",
            "image": "audi-a4avant.jpg",
            "mileage": 2000,
            "fuel_type": "petrol",
            "seats": 5,
            "quantity": 3,
            "price_day": 90,
            "transmission": "automatic"
        },
        {
            "type": "wagon",
            "brand": "Volvo",
            "model": "v60 Cross Country",
            "image": "volvo-crosscountry.jpg",
            "mileage": 3000,
            "fuel_type": "petrol",
            "seats": 5,
            "quantity": 1,
            "price_day": 300,
            "transmission": "automatic"
        },
        {
            "type": "wagon",
            "brand": "Audi",
            "model": "A6",
            "image": "audi-a6.jpg",
            "mileage": 10000,
            "fuel_type": "petrol",
            "seats": 5,
            "quantity": 3,
            "price_day": 300,
            "transmission": "automatic"
        },
        {
            "type": "convertible",
            "brand": "BMW",
            "model": "4 Series",
            "image": "bmw-4series.jpg",
            "mileage": 3000,
            "fuel_type": "petrol",
            "seats": 4,
            "quantity": 1,
            "price_day": 100,
            "transmission": "automatic"
        },
        {
            "type": "convertible",
            "brand": "Audi",
            "model": "S3",
            "image": "audi-s3.jpg",
            "mileage": 8000,
            "fuel_type": "petrol",
            "seats": 4,
            "quantity": 3,
            "price_day": 110,
            "transmission": "automatic"
        },
        {
            "type": "convertible",
            "brand": "Audi",
            "model": "A3",
            "image": "audi-a3.jpg",
            "mileage": 1000,
            "fuel_type": "petrol",
            "seats": 4,
            "quantity": 3,
            "price_day": 300,
            "transmission": "automatic"
        },
        {
            "type": "convertible",
            "brand": "Holden",
            "model": "Cascada",
            "image": "holden-cascada.jpg",
            "mileage": 500,
            "fuel_type": "petrol",
            "seats": 4,
            "quantity": 2,
            "price_day": 90,
            "transmission": "automatic"
        },
        {
            "type": "minivan",
            "brand": "Honda",
            "model": "Odyssey",
            "image": "honda-odyssey.jpg",
            "mileage": 4500,
            "fuel_type": "petrol",
            "seats": 7,
            "quantity": 2,
            "price_day": 100,
            "transmission": "automatic"
        },
        {
            "type": "minivan",
            "brand": "VW",
            "model": "Multivan",
            "image": "VW-multivan.jpg",
            "mileage": 10000,
            "fuel_type": "petrol",
            "seats": 7,
            "quantity": 1,
            "price_day": 120,
            "transmission": "automatic"
        },
        {
            "type": "minivan",
            "brand": "Toyota",
            "model": "Estima",
            "image": "toyota-estima.jpg",
            "mileage": 2000,
            "fuel_type": "petrol",
            "seats": 7,
            "quantity": 2,
            "price_day": 110,
            "transmission": "automatic"
        },
        {
            "type": "minivan",
            "brand": "Hyundai",
            "model": "STARIA",
            "image": "hun-staria.jpg",
            "mileage": 10000,
            "fuel_type": "petrol",
            "seats": 5,
            "quantity": 3,
            "price_day": 300,
            "transmission": "automatic"
        },
        {
            "type": "SUV",
            "brand": "Nissan",
            "model": "Patrol",
            "image": "nissan-patrol.jpg",
            "mileage": 1000,
            "fuel_type": "disel",
            "seats": 5,
            "quantity": 1,
            "price_day": 80,
            "transmission": "manual"
        },
        {
            "type": "sedan",
            "brand": "Honda",
            "model": "Civic",
            "image": "honda-civic.jpg",
            "mileage": 8900,
            "fuel_type": "petrol",
            "seats": 5,
            "quantity": 2,
            "price_day": 60,
            "transmission": "manual"
        },
        {
            "type": "sedan",
            "brand": "Holden",
            "model": "Astra",
            "image": "holden-astra.jpg",
            "mileage": 30000,
            "fuel_type": "petrol",
            "seats": 5,
            "quantity": 2,
            "price_day": 60,
            "transmission": "manual"
        },
        {
            "type": "convertible",
            "brand": "Ford",
            "model": "Mustang",
            "image": "ford-mustang.jpg",
            "mileage": 7000,
            "fuel_type": "petrol",
            "seats": 4,
            "quantity": 1,
            "price_day": 100,
            "transmission": "automatic"
        },
        {
            "type": "wagon",
            "brand": "Mazda",
            "model": "6",
            "image": "mazda-6.jpg",
            "mileage": 400,
            "fuel_type": "petrol",
            "seats": 5,
            "quantity": 1,
            "price_day": 80,
            "transmission": "automatic"
        },
        {
            "type": "wagon",
            "brand": "VW",
            "model": "Golf",
            "image": "vw-golf.jpg",
            "mileage": 9000,
            "fuel_type": "petrol",
            "seats": 5,
            "quantity": 1,
            "price_day": 80,
            "transmission": "automatic"
        }
    ]
}